odoo/addons/l10n_es_aeat_sii_oss/README.rst
odoo/addons/l10n_es_aeat_sii_oss/__init__.py
odoo/addons/l10n_es_aeat_sii_oss/__manifest__.py
odoo/addons/l10n_es_aeat_sii_oss/data/aeat_sii_mapping_registration_keys_data.xml
odoo/addons/l10n_es_aeat_sii_oss/i18n/ca.po
odoo/addons/l10n_es_aeat_sii_oss/i18n/es.po
odoo/addons/l10n_es_aeat_sii_oss/i18n/l10n_es_aeat_sii_oss.pot
odoo/addons/l10n_es_aeat_sii_oss/models/__init__.py
odoo/addons/l10n_es_aeat_sii_oss/models/account_move.py
odoo/addons/l10n_es_aeat_sii_oss/readme/CONFIGURE.md
odoo/addons/l10n_es_aeat_sii_oss/readme/CONTRIBUTORS.md
odoo/addons/l10n_es_aeat_sii_oss/readme/DESCRIPTION.md
odoo/addons/l10n_es_aeat_sii_oss/readme/INSTALL.md
odoo/addons/l10n_es_aeat_sii_oss/static/description/icon.png
odoo/addons/l10n_es_aeat_sii_oss/static/description/icon_source.svg
odoo/addons/l10n_es_aeat_sii_oss/static/description/index.html
odoo/addons/l10n_es_aeat_sii_oss/tests/__init__.py
odoo/addons/l10n_es_aeat_sii_oss/tests/test_l10n_es_aeat_sii.py
odoo_addon_l10n_es_aeat_sii_oss-18.0.1.0.0.2.dist-info/METADATA
odoo_addon_l10n_es_aeat_sii_oss-18.0.1.0.0.2.dist-info/WHEEL
odoo_addon_l10n_es_aeat_sii_oss-18.0.1.0.0.2.dist-info/top_level.txt
odoo_addon_l10n_es_aeat_sii_oss-18.0.1.0.0.2.dist-info/RECORD
