Metadata-Version: 2.1
Name: odoo-addon-l10n_es_aeat_sii_oss
Version: 18.0.1.0.0.2
Requires-Python: >=3.10
Requires-Dist: odoo-addon-account_fiscal_position_partner_type==18.0.*
Requires-Dist: odoo-addon-l10n_es_aeat_sii_oca==18.0.*
Requires-Dist: odoo-addon-l10n_eu_oss_oca==18.0.*
Requires-Dist: odoo==18.0.*
Summary: =?utf-8?q?Suministro_Inmediato_de_Informaci=C3=B3n_en_el_IVA=3A_OSS?=
Home-page: https://github.com/OCA/l10n-spain
License: AGPL-3
Author: FactorLibre, Tecnativa, Odoo Community Association (OCA)
Author-email: support@odoo-community.org
Classifier: Programming Language :: Python
Classifier: Framework :: Odoo
Classifier: Framework :: Odoo :: 18.0
Classifier: License :: OSI Approved :: GNU Affero General Public License v3
Classifier: Development Status :: 5 - Production/Stable
